PyCameraList/__init__.py
PyCameraList/camera_device.cp36-win_amd64.pyd
PyCameraList-1.0.0.dist-info/DESCRIPTION.rst
PyCameraList-1.0.0.dist-info/METADATA
PyCameraList-1.0.0.dist-info/RECORD
PyCameraList-1.0.0.dist-info/WHEEL
PyCameraList-1.0.0.dist-info/metadata.json
PyCameraList-1.0.0.dist-info/top_level.txt
