Metadata-Version: 2.0
Name: PyCameraList
Version: 1.0.0
Summary: List all camera/audio sources for windows users.
Home-page: UNKNOWN
Author: Peter Jiang
License: UNKNOWN
Platform: UNKNOWN
Requires-Python: >=3.6
